README.rst
setup.py
callerlib/__init__.py
callerlib/base.py
callerlib/conf.py
callerlib/management.py
callerlib.egg-info/PKG-INFO
callerlib.egg-info/SOURCES.txt
callerlib.egg-info/dependency_links.txt
callerlib.egg-info/entry_points.txt
callerlib.egg-info/requires.txt
callerlib.egg-info/top_level.txt
callerlib/template/caller.py
callerlib/template/settings.py
callerlib/template/logs/.keep