Metadata-Version: 1.1
Name: callerlib
Version: 0.1.2
Summary: A sip caller robotframework library.
Home-page: https://bitbucket.org/PekaTeam/callerlib
Author: Pavel Fedorov
Author-email: studentofsut@gmail.com
License: BSD License
Platform: UNKNOWN
Classifier: Environment :: Console
Classifier: Intended Audience :: Telecommunications Industry
Classifier: License :: Freeware
Classifier: Natural Language :: Russian
Classifier: Operating System :: OS Independent
Classifier: Programming Language :: Python :: 2
